{"object":{"name":"Swoole\\Coroutine\\Socket"},"comment":"协程版socket","namespace":"Swoole\\Coroutine","isFinal":1,"interfaces":[],"consts":[],"properties":{"errCode":{"access":"public","type":"int","comment":"错误码","isStatic":false,"value":0}},"methods":{"__construct":{"access":"public","comment":"构造socket对象","isStatic":false,"return":"","example":"","parameters":{"domain":{"comment":"使用的协议域(AF_INET、AF_INET6、AF_UNIX)","type":"int","options":[]},"type":{"comment":"使用的socket类型(SOCK_STREAM、SOCK_DGRAM、SOCK_RAW)","type":"int","options":[]},"protocol":{"comment":"IPPROTO_TCP、IPPROTO_UDP、IPPROTO_STCP、IPPROTO_TIPC","type":"int","options":[]}}},"bind":{"access":"public","comment":"绑定地址和端口","isStatic":false,"return":"bool","example":"","parameters":{"address":{"comment":"绑定的地址(一般是IP地址)","type":"string","options":[]},"port":{"comment":"绑定的端口","type":"int","options":[]}}},"listen":{"access":"public","comment":"监听socket","isStatic":false,"return":"bool","example":"","parameters":{"backlog":{"comment":"监听队列的长度","type":"int","options":[],"value":0}}},"accept":{"access":"public","comment":"接受客户端发起的连接","isStatic":false,"return":"Coroutine\\Socket|false","example":"","parameters":{"timeout":{"comment":"设置超时，默认为-1表示永不超时","type":"float","options":[]}}},"connect":{"access":"public","comment":"连接到目标服务器","isStatic":false,"return":"bool","example":"","parameters":{"host":{"comment":"目标服务器的地址","type":"string","options":[]},"port":{"comment":"目标服务器端口","type":"int","options":[]},"timeout":{"comment":"超时时间，底层会设置定时器，在规定的时间内未能建立连接","type":"float","options":[]}}},"recv":{"access":"public","comment":"接受对端数据","isStatic":false,"return":"string|bool","example":"","parameters":{"timeout":{"comment":"超时时间","type":"float","options":[]}}},"send":{"access":"public","comment":"向对端发送数据","isStatic":false,"return":"int|bool","example":"","parameters":{"data":{"comment":"要发送的数据内容，可以为文本或二进制数据","type":"string","options":[]},"timeout":{"comment":"设置超时时间，默认为-1表示永不超时","type":"float","options":[]}}},"recvfrom":{"access":"public","comment":"接收数据，并设置来源主机的地址和端口","isStatic":false,"return":"string|false","example":"","parameters":{"peername":{"comment":"对端地址和端口，引用类型。函数成功返回时会设置为数组，包括address和port两个元素","type":"array","options":[]},"timeout":{"comment":"超时时间","type":"float","options":[]}}},"sendto":{"access":"public","comment":"向指定的地址和端口发送数据","isStatic":false,"return":"int|false","example":"","parameters":{"addr":{"comment":"目标主机的IP地址或UnixSocket路径","type":"string","options":[]},"port":{"comment":"目标主机的端口，发送广播时可以为0","type":"int","options":[]},"data":{"comment":"发送的数据，可以为文本或二进制内容","type":"string","options":[]}}},"getpeername":{"access":"public","comment":"获取socket的对端地址和端口信息","isStatic":false,"return":"array|false","example":"","parameters":[]},"getsockname":{"access":"public","comment":"获取socket的地址和端口信息","isStatic":false,"return":"array|bool","example":"","parameters":[]},"getSocket":{"access":"public","comment":"获取socket连接句柄","isStatic":false,"return":"int","example":"","parameters":[]},"close":{"access":"public","comment":"关闭socket","isStatic":false,"return":"bool","example":"","parameters":[]}}}