{"object":{"name":"YafX_Response_Abstract"},"comment":"(Yaf >= 3.0.2)\nClass yaf_Response_Abstract","namespace":"","isAbstract":1,"consts":[],"properties":{"_header":{"access":"protected","type":"unknown","comment":"(Yaf >= 3.0.2)\n\u54cd\u5e94\u62a5\u5934","isStatic":false,"example":""},"_body":{"access":"protected","type":"unknown","comment":"(Yaf >= 3.0.2)\n\u54cd\u5e94\u6b63\u6587","isStatic":false,"example":""},"_sendheader":{"access":"protected","type":"unknown","comment":"(Yaf >= 3.0.2)\n\u662f\u5426\u5f00\u542f\u5df2\u8f93\u51fa\u54cd\u5e94\u62a5\u5934\u68c0\u6d4b","isStatic":false,"value":0,"example":""},"_response_code":{"access":"protected","type":"unknown","comment":"(Yaf >= 3.0.2)\n\u54cd\u5e94\u72b6\u6001\u7801","isStatic":false,"example":""},"DEFAULT_BODY":{"access":"public","type":"unknown","comment":"(Yaf >= 3.0.2)\n\u9ed8\u8ba4\u54cd\u5e94\u6b63\u6587\u5b9e\u4f53\u540d","isStatic":false,"value":"content","example":""}},"methods":{"__construct":{"access":"public","comment":"(Yaf >= 3.0.2)\n\u6784\u9020\u65b9\u6cd5","isStatic":false,"return":"","example":"","parameters":[]},"__destruct":{"access":"public","comment":"(Yaf >= 3.0.2)\n\u6790\u6784\u65b9\u6cd5","isStatic":false,"return":"","example":"","parameters":[]},"__clone":{"access":"private","comment":"(Yaf >= 3.0.2)\n\u91cd\u7f6e__clone\u9b54\u672f\u65b9\u6cd5","isStatic":false,"return":"","example":"","parameters":[]},"__toString":{"access":"public","comment":"(Yaf >= 3.0.2)\n\u8fd4\u56de\u54cd\u5e94\u6b63\u6587\u7684\u5b57\u7b26\u4e32","isStatic":false,"return":"","example":"","parameters":[]},"setBody":{"access":"public","comment":"(Yaf >= 3.0.2)\n\u8bbe\u7f6e\u7c7b\u578b\u4e3a$name\u7684\u54cd\u5e94\u6b63\u6587\u5185\u5bb9","isStatic":false,"return":"","example":"","parameters":{"body":{"comment":"\u54cd\u5e94\u6b63\u6587\u5185\u5bb9\uff08\u53ef\u8986\u76d6\u539f\u6765\u7684\uff09","type":"string","options":[]},"name":{"comment":"\u54cd\u5e94\u6b63\u6587\u7c7b\u578b\uff0c\u9ed8\u8ba4\u4e3acontent","type":"string","options":[],"value":"content"}}},"getBody":{"access":"public","comment":"(Yaf >= 3.0.2)\n\u83b7\u53d6\u7c7b\u578b\u4e3a$name\u7684\u54cd\u5e94\u6b63\u6587\u5185\u5bb9","isStatic":false,"return":"","example":"","parameters":{"name":{"comment":"\u54cd\u5e94\u6b63\u6587\u7c7b\u578b\uff0c\u9ed8\u8ba4\u4e3acontent","type":"string","options":[],"value":"content"}}},"appendBody":{"access":"public","comment":"(Yaf >= 3.0.2)\n\u8bbe\u7f6e\u7c7b\u578b\u4e3a$name\u7684\u54cd\u5e94\u6b63\u6587\u5185\u5bb9, \u5982\u5df2\u5b58\u5728\uff0c\u5219\u8ffd\u52a0\u5230\u539f\u6765\u6b63\u6587\u7684\u540e\u9762","isStatic":false,"return":"","example":"","parameters":{"body":{"comment":"\u54cd\u5e94\u6b63\u6587\u5185\u5bb9\uff08\u53ef\u8ffd\u52a0\uff09","type":"string","options":[]},"name":{"comment":"\u54cd\u5e94\u6b63\u6587\u7c7b\u578b\uff0c\u9ed8\u8ba4\u4e3acontent","type":"string","options":[],"value":null}}},"prependBody":{"access":"public","comment":"(Yaf >= 3.0.2)\n\u8bbe\u7f6e\u7c7b\u578b\u4e3a$name\u7684\u54cd\u5e94\u6b63\u6587\u5185\u5bb9, \u5982\u5df2\u5b58\u5728\uff0c\u5219\u8ffd\u52a0\u5230\u539f\u6765\u6b63\u6587\u7684\u524d\u9762","isStatic":false,"return":"","example":"","parameters":{"body":{"comment":"\u54cd\u5e94\u6b63\u6587\u5185\u5bb9\uff08\u53ef\u8ffd\u52a0\uff09","type":"string","options":[]},"name":{"comment":"\u54cd\u5e94\u6b63\u6587\u7c7b\u578b\uff0c\u9ed8\u8ba4\u4e3acontent","type":"string","options":[],"value":null}}},"clearBody":{"access":"public","comment":"(Yaf >= 3.0.2)\n\u6e05\u7a7a\u54cd\u5e94\u6b63\u6587","isStatic":false,"return":"","example":"","parameters":[]},"getHeader":{"access":"public","comment":"(Yaf >= 3.0.2)\n\u83b7\u53d6\u54cd\u5e94\u62a5\u5934","isStatic":false,"return":"","example":"","parameters":[]},"setAllHeaders":{"access":"public","comment":"(Yaf >= 3.0.2)\n\u83b7\u53d6\u6240\u6709\u54cd\u5e94\u62a5\u5934","isStatic":false,"return":"","example":"","parameters":[]},"setHeader":{"access":"public","comment":"(Yaf >= 3.0.2)\n\u8bbe\u7f6e\u54cd\u5e94\u62a5\u5934","isStatic":false,"return":"","example":"","parameters":[]},"clearHeaders":{"access":"public","comment":"(Yaf >= 3.0.2)\n\u6e05\u7a7a\u54cd\u5e94\u62a5\u5934","isStatic":false,"return":"","example":"","parameters":[]},"setRedirect":{"access":"public","comment":"(Yaf >= 3.0.2)\n\u5c06\u5f53\u524d\u8bf7\u6c42\u91cd\u5b9a\u5411\u5230\u6307\u5b9a\u7684URL\uff08\u5185\u90e8\u5b9e\u73b0\u662f\u901a\u8fc7\u53d1\u9001Location\u62a5\u5934\u5b9e\u73b0\uff0c\u5982\uff1aheader(\"Location:http\/\/www.phpboy.net\/\"\uff09\uff09","isStatic":false,"return":"","example":"","parameters":{"url":{"comment":"\u91cd\u5b9a\u5411\u7684\u7edd\u5bf9URL","type":"string","options":[]}}},"response":{"access":"public","comment":"(Yaf >= 3.0.2)\n\u8f93\u51fa\u6240\u6709\u7684\u54cd\u5e94\u6b63\u6587","isStatic":false,"return":"","example":"","parameters":[]}}}